
[{
		"categoryId": 1,
		"categoryTitle": "EPL",
		"categoryItemList": [{
  "bannerCategoryId": "1",
        "fileUrl": "https://www.livedoomovies.com/02_PremierHD1_480p/chunklist.m3u8",
    "id": 8,
     "imageUrl": "https://i.ytimg.com/vi/7nEybJXT2O4/maxresdefault.jpg",
    "movieName": "WEST BROMWICH ALBION VS ASTON VILA"
},
  {
    "bannerCategoryId": "1",
       "fileUrl": "http://46f136e2.kazaktelekom.com/iptv/2GU6SMVG2ARSBF/2545/index.m3u8",
    "id": 8,
     "imageUrl": "https://i.ytimg.com/vi/7nEybJXT2O4/maxresdefault.jpg",
    "movieName": "WEST BROMWICH ALBION VS ASTON VILA"
}]
	},
				     
		
		
        {		     
		"categoryId": 2,
		"categoryTitle": "LA LIGA",
		"categoryItemList": [

   {
    "bannerCategoryId": "3",
    "fileUrl": "http://s4ak2ost.rostelekom.xyz/iptv/8BYEXQ5P4TPETX/6124/index.m3u8",
    "id": 3,
  "imageUrl": "https://i.ytimg.com/vi/njsRAWkVy2M/maxresdefault.jpg",
    "movieName": "CADIZ VS GETAFE"
  },
     {
    "bannerCategoryId": "3",
    "fileUrl": "http://s4ak2ost.rostelekom.xyz/iptv/8BYEXQ5P4TPETX/6124/index.m3u8",
    "id": 3,
  "imageUrl": "https://i.ytimg.com/vi/njsRAWkVy2M/maxresdefault.jpg",
    "movieName": "CADIZ VS GETAFE"
  },
      {
    "bannerCategoryId": "3",
    "fileUrl": "",
    "id": 4,
  "imageUrl": "https://i.ytimg.com/vi/VaHhUwZQBUI/maxresdefault.jpg",
    "movieName": "EIBAR VS REAL MADRID"
  },
      {
    "bannerCategoryId": "3",
    "fileUrl": "",
    "id": 5,
  "imageUrl": "https://i.ytimg.com/vi/VaHhUwZQBUI/maxresdefault.jpg",
    "movieName": "EIBAR VS REAL MADRID"
  }
		
		]
	}
]
